quten.py
quten_optimizer-1.0.0.dist-info/licenses/LICENSE
scripts/test_build.sh
test_ablation_results/Adam.json
test_ablation_results/QUTEN-Full.json
test_ablation_results/QUTEN-NoTunneling.json
quten_optimizer-1.0.0.dist-info/METADATA
quten_optimizer-1.0.0.dist-info/WHEEL
quten_optimizer-1.0.0.dist-info/top_level.txt
quten_optimizer-1.0.0.dist-info/RECORD
